README.rst
setup.py
argv/__init__.py
argv/flags.py
argv/iterables.py
argv/testing.py
argv/tokens.py
argv.egg-info/PKG-INFO
argv.egg-info/SOURCES.txt
argv.egg-info/dependency_links.txt
argv.egg-info/top_level.txt
argv/parsers/__init__.py
argv/parsers/boolean.py
argv/parsers/inferential.py