Metadata-Version: 1.1
Name: argv
Version: 0.0.3
Summary: Simpler command line argument parsing
Home-page: https://github.com/chbrown/argv
Author: Christopher Brown
Author-email: io@henrian.com
License: Copyright (c) 2013 Christopher Brown
